Workbook

Sheet Roadmap
A1: ID | B1: Task | C1: Module | D1: Priority | E1: Status | F1: Source | G1: Notes | H1: Map Layer | I1: Map Block
A2: CAL-0 | B2: the two shipped defects, before any new feature: add tenantId (+ date range) to GET /api/calendar/events; partition calendar-storage-v1 by tenant and reset on logout/switch/impersonation. Verify: tenant A's events never appear for B; switching tenants clears selections and cached events. | C2: Calendar | D2: P0 | E2: Open | F2: coral-calendar.md:64 | H2: L2 | I2: Calendar module
A3: CAL-1 | B3: the blocker. Mirror api/email/connect/google/route.ts: a dedicated OAuth consent route requesting auth/calendar scope (incremental auth, access_type=offline, prompt=consent for a refresh token), a callback storing tokens bound to (userId, tenantId), and a Connect Google Calendar button + connecte... | C3: Calendar | D3: P0 | E3: Open | F3: coral-calendar.md:65 | H3: L2 | I3: Calendar module
A4: ATT-1 | B4: add to StorageProvider / BlobStorageProvider: | C4: Email attachments | D4: P0 | E4: Done | F4: coral-email-attachments-bug.md:39 | H4: L1 | I4: document engine — attachments
A5: ATT-2 | B5: send-invoice.ts and send-quote.ts. Keep the t_${tenantId}/ tenant check (it's correct and necessary). | C5: Email attachments | D5: P0 | E5: Done | F5: coral-email-attachments-bug.md:52 | H5: L1 | I5: document engine — attachments
A6: ATT-3 | B6: if any selected attachment cannot be fetched: | C6: Email attachments | D6: P0 | E6: Done | F6: coral-email-attachments-bug.md:54 | H6: L1 | I6: document engine — attachments
A7: N1-GRID-CELL-RACE | B7: Sales grid: typing a name then clicking the date cell loses the typed text — whole-row read-modify-write race between cell editors | C7: Engine · Grid | D7: P0 | E7: Open | F7: no spec yet | G7: Needs spec | H7: L3 | I7: grid — write race
A8: PROT-5 | B8: open the existing send modal prefilled (to = supplier email, subject, body, attachment). Do not build a second mail composer. Recipient resolution: supplier's invoice/contact email; if missing, open with an empty To and flag it. CC Florin (the sending tenant owner) by default — his own copy is an... | C8: Finance · Invoice protest | D8: P0 | E8: Open | F8: coral-invoice-protest.md:30 | H8: L3 | I8: Finance — invoice protest
A9: PI-LINES-1 | B9: create getInvoiceLines(page) and use it in every surface (engine view, engine edit, PageModal, PDF template, totals calculation). Resolution order: blocks[financial-row] → properties.invoiceLines (parse the JSON string, tolerate already-parsed arrays) → peppolDetail.lines → []. No component parse... | C9: Finance · Purchase invoices | D9: P0 | E9: Open | F9: coral-purchase-invoice-lines.md:19 | H9: L3 | I9: Finance — purchase invoices
A10: PI-LINES-2 | B10: at import (Peppol inbox + scan), write the lines as financial-row blocks in addition to keeping invoiceLines for provenance. New invoices then render immediately with no edit-and-save ritual. Keep invoiceLines as the raw as-received record — useful for audit and for re-deriving if a mapping bug i... | C10: Finance · Purchase invoices | D10: P0 | E10: Open | F10: coral-purchase-invoice-lines.md:20 | H10: L3 | I10: Finance — purchase invoices
A11: TS-1 | B11: one tenant-scoped aggregation endpoint powering every view/export. Filters: period (from/to, presets: this week / last week / month / custom), worker(s), project(s), team, approval status, entry source (clocked / manual / adjusted). Returns per-entry rows and rollups: hours per worker, per projec... | C11: HR · Timesheet reporting | D11: P0 | E11: Done | F11: coral-timesheet-reporting.md:30 | G11: afbf405 | H11: L3 | I11: HR — timesheets
A12: TS-2b | B12: approval actions exist but are write-only: there is no surface showing what is pending, what was approved/denied, by whom, or when. That makes the approval step unverifiable — and unverifiable approvals are worthless for payroll or a dispute. Implement all of the below as filter/grouping states o... | C12: HR · Timesheet reporting | D12: P0 | E12: Open | F12: coral-timesheet-reporting.md:48 | H12: L3 | I12: HR — timesheets
A13: TS-3 | B13: make the project attribution reliable: | C13: HR · Timesheet reporting | D13: P0 | E13: Open | F13: coral-timesheet-reporting.md:54 | H13: L3 | I13: HR — timesheets
A14: TS-8 | B14: (Florin decision, 2026-07-26) | C14: HR · Timesheet reporting | D14: P0 | E14: Open | F14: coral-timesheet-reporting.md:69 | H14: L3 | I14: HR — timesheets
A15: TSP-1 | B15: replace hrList('clock-entries') with GET /api/hr/timesheet-reports, passing the filter state as query params. Keep the existing approve/deny path (hrUpdate). Default period = this week — never fetch all history by default (today it does). Render summary into StatCards and entries into the existin... | C15: HR · Timesheets page | D15: P0 | E15: In progress | F15: coral-timesheets-page.md:64 | H15: L3 | I15: HR — timesheets page
A16: TSP-5 | B16: inline approve/deny + multi-select bulk with confirmation; reason-for-approval flags visible per row (late · manual · off-geofence · missing clock-out) — a queue without why is just a list; approver + timestamp columns in the approved/denied views; approvals reversible with a trail. Approved and ... | C16: HR · Timesheets page | D16: P0 | E16: Open | F16: coral-timesheets-page.md:68 | H16: L3 | I16: HR — timesheets page
A17: TSP-B1 | B17: (this is why the table looks empty / shows only a few rows). timesheet-reports/route.ts:36,60 applies where.userId = { in: getAccessibleUserIds(...) } unconditionally, and getAccessibleUserIds returns only the caller's own id unless they lead an HrTeam. So a TENANT_OWNER is scoped like a workforc... | C17: HR · Timesheets page | D17: P0 | E17: Done | F17: coral-timesheets-page.md:57 | H17: L3 | I17: HR — timesheets page
A18: TSP-B2 | B18: the page calls useTranslations('Hr.timesheets') (page.tsx:40) but the Hr.timesheets. keys don't exist in messages/{en,nl,fr}.json, so next-intl renders the key paths (Hr.timesheets.title, HR.TIMESHEETS.TOTALHOURS). Same class as TASKS-I18N-NAMES. Add the full block in all three languages using th... | C18: HR · Timesheets page | D18: P0 | E18: Done | F18: coral-timesheets-page.md:58 | H18: L3 | I18: HR — timesheets page
A19: MEM-1 | B19: (cheapest real win — do this first) | C19: Performance · Memory | D19: P0 | E19: Done | F19: coral-memory-investigation.md:37 | H19: L1 | I19: read path — pageIndex, hydration
A20: MEM-3a | B20: ADD THE INDEX — getGlobalPageIndex() + pageIndex store slice; purely additive, do first | C20: Performance · Memory | D20: P0 | E20: Open | F20: coral-mem3-lazy-data.md | H20: L1 | I20: read path — pageIndex, hydration
A21: PROJ-1 | B21: verify the crash is gone (ADMIN-QUERYCLIENT-PROVIDER) and finish its tenant guarding (scoped query keys + clear-on-switch). Nothing else matters until the detail opens reliably. | C21: Projects | D21: P0 | E21: In progress | F21: coral-project-module.md:29 | H21: L3 | I21: Projects
A22: N3-IDLE-CRASH | B22: App idle for a long time crashes: TypeError: Load failed (Safari fetch). Leading hypothesis: Neon autosuspend | C22: Reliability | D22: P0 | E22: Open | F22: coral-memory-investigation.md | G22: Evidence-first | H22: L3 | I22: grid
A23: RCPT-L4b-1 | B23: add onComplete(summary) to the modal; the parent refreshes the store and switches to the Inbox / Te verwerken view. Summary shape: { total, ready, needsReview, failed }. | C23: Scan · Receipt bulk | D23: P0 | E23: Done | F23: coral-receipt-bulk.md:77 | H23: L3 | I23: Expenses — receipts
A24: RCPT-L4b-2 | B24: after each job, insert/refresh the created page in the store so the grid updates as documents complete, not on reload. (Server-first create + no client sync is the same gap that made column visibility "not stick" — see pd.md FORCING FUNCTIONS #1.) | C24: Scan · Receipt bulk | D24: P0 | E24: Done | F24: coral-receipt-bulk.md:78 | H24: L3 | I24: Expenses — receipts
A25: A1 | B25: implement the MISSING submitLateEntry server action in src/app/actions/timesheets.ts (Planner-traced: it doesn't exist → TypeError: s is not a function → "Failed to submit late entry"). Create a PENDING ClockEntry from the input LateEntryCard already sends (targetUserId, clockIn/OutTime, location... | C25: Triage / core | D25: P0 | E25: Done | F25: ground-zero-triage.md:716 | H25: L3 | I25: grid
A26: ADMIN-QUERYCLIENT-PROVIDER | B26: ROOT CAUSE (Planner-traced from the live console): useClockEntries (now React Query) + useScheduledShifts are imported by src/components/admin/database/components/ProjectDetailView.tsx (L12-13, added by workforce-scoping commit 9c0b5ff). The admin app (AdminLayout) has NO QueryClientProvider — on... | C26: Triage / core | D26: P0 | E26: Done | F26: ground-zero-triage.md:663 | H26: ⟂ | I26: deployment / ops
A27: DATA-PERSIST-INTEGRITY | B27: make edits durable and un-clobberable. This is the #1 data-safety fix now that Coral holds real work. | C27: Triage / core | D27: P0 | E27: Open | F27: ground-zero-triage.md:645 | H27: ⟂ | I27: data model
A28: HR-NAV-ROUTES-TO-WORKHUB | B28: STILL BROKEN (Florin re-confirmed 2026-07-12: "click HR still routes to timetracker") — NOT YET APPLIED. The sidebar-order/persistence work (commit 5202fca) landed but this href change was skipped. useSidebarStore.ts:67 still reads href: '/admin/hr/time-tracker' → that route is redirect('/workhub... | C28: Triage / core | D28: P0 | E28: Done | F28: ground-zero-triage.md:412 | H28: L3 | I28: HR / Workforce
A29: OCC-1-REBASELINE | B29: one-line fix, do this first, it alone stops the permanent-conflict loop. | C29: Triage / core | D29: P0 | E29: Done | F29: ground-zero-triage.md:83 | H29: L1 | I29: write path — concurrency
A30: OCC-11-BLOCKSVERSION-REPLACES-HASHING | B30: (ESCALATION — only if OCC-9b doesn't hold. Then it supersedes OCC-9 entirely.) | C30: Triage / core | D30: P0 | E30: Done | F30: ground-zero-triage.md:161 | H30: L1 | I30: write path — concurrency
A31: OCC-12-BLOCKSVERSION-LOST-ITS-QUALIFIERS | B31: (Florin: "OCC-11 didn't cut it either" — 2026-07-27) | C31: Triage / core | D31: P0 | E31: Done | F31: ground-zero-triage.md:178 | H31: L1 | I31: write path — concurrency
A32: OCC-15-SYNC-QUEUE-HAS-NO-SINGLE-FLIGHT-LOCK | B32: (Florin, 2026-07-27, after OCC-14 fixed the general case: "I edited a quote, deleted lines, no protest. The sync issue fires when I edit text.") | C32: Triage / core | D32: P0 | E32: Done | F32: ground-zero-triage.md:227 | H32: L1 | I32: write path — concurrency
A33: OCC-2-SYSTEM-WRITE-TAG | B33: mark non-human writes so they're never reported as "someone else." | C33: Triage / core | D33: P0 | E33: Done | F33: ground-zero-triage.md:90 | H33: L1 | I33: write path — concurrency
A34: OCC-6-BLOCKS-GUARD-TOO-BROAD | B34: REGRESSION — reproducible on EVERY new quote (Florin live, 2026-07-26). | C34: Triage / core | D34: P0 | E34: Done | F34: ground-zero-triage.md:113 | H34: L1 | I34: write path — concurrency
... A53: ATT-4 | B53: the success toast lists the attached filenames, and the sent-record/audit entry stores the attachment list. Then "did the client get the plan?" is answerable from the record instead of from memory. | C53: Email attachments | D53: P1 | E53: Open | F53: coral-email-attachments-bug.md:59 | H53: L1 | I53: document engine — attachments
A54: N2-RELATION-LINK-ICON | B54: Link-back icon on relation fields does not route on many surfaces | C54: Engine · Relations | D54: P1 | E54: Open | F54: no spec yet | G54: Not yet investigated | H54: L3 | I54: grid
A55: PROT-1 | B55: a Protest action on the purchase-invoice record detail (and as a row action in the expenses grid). Opens a small dialog: | C55: Finance · Invoice protest | D55: P1 | E55: Open | F55: coral-invoice-protest.md:19 | H55: L3 | I55: Finance — invoice protest
A56: PROT-2 | B56: resolve in this order: supplier record's language property → tenant default → nl. Support NL / FR / EN (add DE only if a supplier needs it). If the supplier has no language set, default to NL and show which language was chosen in the modal, so a wrong pick is visible before sending, not after. Be... | C56: Finance · Invoice protest | D56: P1 | E56: Open | F56: coral-invoice-protest.md:23 | H56: L3 | I56: Finance — invoice protest
A57: PROT-3 | B57: one template per language (NL / FR / EN), in messages/.json (not hardcoded), composed of: salutation → statement of protest with invoice number, invoice date, amount, supplier name → the reason paragraph (from PROT-1) → free-text detail → what is expected (a credit note AND a corrected invoice — ... | C57: Finance · Invoice protest | D57: P1 | E57: Open | F57: coral-invoice-protest.md:24 | H57: L3 | I57: Finance — invoice protest
A58: PROT-4 | B58: attach the original invoice document (the stored purchase-invoice PDF / scan / Peppol-rendered PDF) to the outgoing mail. Serve via the authenticated /api/files/<key> route — never a bare blob key or public URL (same trap as RECEIPT-BONNETJE-LINK). If the record has no stored document, allow send... | C58: Finance · Invoice protest | D58: P1 | E58: Open | F58: coral-invoice-protest.md:29 | H58: L3 | I58: Finance — invoice protest
A59: PROT-6 | B59: on send, write to the invoice record: protestStatus (geprotesteerd), protestedAt, protestReason, protestedBy, disputedAmount (if partial), and a link/id to the sent mail. Surface a "Geprotesteerd" badge in the expenses grid and on the record. Additive properties only (pd.md). Also: exclude protes... | C59: Finance · Invoice protest | D59: P1 | E59: Open | F59: coral-invoice-protest.md:31 | H59: L3 | I59: Finance — invoice protest
A60: PI-ART-1 | B60: each purchase-invoice line description becomes a searchable field against db-articles (reuse the quotation engine's existing article SearchableSelect — do not build a second search). Typing/opening a line offers matching articles; fuzzy match on description, with supplier + unit as tie-breakers. | C60: Finance · Purchase invoices | D60: P1 | E60: Open | F60: coral-purchase-invoice-lines.md:32 | H60: L3 | I60: Finance — purchase invoices
A61: PI-ART-2 | B61: when a line matches an existing article, the modal shows: the article (name, unit, current purchase price, last-updated date) beside the invoice line (description, qty, unit, unit price, VAT), and offers: | C61: Finance · Purchase invoices | D61: P1 | E61: Open | F61: coral-purchase-invoice-lines.md:33 | H61: L3 | I61: Finance — purchase invoices
A62: PI-ART-3 | B62: when no match exists, "Add to article library" directly from the line (and from the modal). Prefill from the invoice line: description → name, unit, unit price → purchase price, VAT rate, supplier (from the invoice), artikelgroep (let the user pick; suggest from the supplier's usual group). Creat... | C62: Finance · Purchase invoices | D62: P1 | E62: Open | F62: coral-purchase-invoice-lines.md:38 | H62: L3 | I62: Finance — purchase invoices
A63: PI-ART-6 | B63: when an article is pulled into a quotation line, compare the article's stored price against the most recently observed purchase price (preferred supplier, or the cheapest — see below). If they differ, show an inline, non-blocking indicator on the line: "Library €12.40 · last bought €13.10 (+5.6%)... | C63: Finance · Purchase invoices | D63: P1 | E63: Open | F63: coral-purchase-invoice-lines.md:60 | H63: L3 | I63: Finance — purchase invoices
A64: TS-2 | B64: (Florin, 2026-07-27: "I do want all crystallised in one working page… reporting, filtering and approval flow added to the timesheets page without uselessly creating others.") | C64: HR · Timesheet reporting | D64: P1 | E64: Open | F64: coral-timesheet-reporting.md:32 | H64: L3 | I64: HR — timesheets
A65: TS-4 | B65: from any filtered result: | C65: HR · Timesheet reporting | D65: P1 | E65: Open | F65: coral-timesheet-reporting.md:60 | H65: L3 | I65: HR — timesheets
A66: TS-5 | B66: ClockEntry.photos and ShiftAttachment are captured but not usable in bulk. Build: a gallery per entry/shift/project/period; thumbnails in the report row; bulk download as ZIP (per project or period); attach selected photos into the werkbon PDF (TS-4) as evidence; and push relevant photos through ... | C66: HR · Timesheet reporting | D66: P1 | E66: Open | F66: coral-timesheet-reporting.md:65 | H66: L3 | I66: HR — timesheets
... A71: TSP-B3 | B71: the Period control must include a custom date-range picker, not just presets. Reuse the existing src/components/ui/CustomDatePicker.tsx — do not introduce another calendar component or a third date-picking pattern. Selecting a range sets from/to in the URL params that already drive the API. | C71: HR · Timesheets page | D71: P1 | E71: Open | F71: coral-timesheets-page.md:59 | H71: L3 | I71: HR — timesheets page
A72: MEM-2 | C72: Performance · Memory | D72: P1 | E72: Open | F72: coral-memory-investigation.md:40 | H72: L1 | I72: read path — pageIndex, hydration
A73: MEM-3 | B73: (the root fix) | C73: Performance · Memory | D73: P1 | E73: In progress | F73: coral-memory-investigation.md:43 | H73: L1 | I73: read path — pageIndex, hydration
A74: MEM-3b | B74: SPLIT THE SERVER ACTION — schemas without pages + getDatabasePages(dbId) | C74: Performance · Memory | D74: P1 | E74: Open | F74: coral-mem3-lazy-data.md | H74: L1 | I74: read path — pageIndex, hydration
A75: MEM-3c | B75: LAZY-LOAD CONTENT PER DATABASE — behind a feature flag; the actual win | C75: Performance · Memory | D75: P1 | E75: Open | F75: coral-mem3-lazy-data.md | H75: L1 | I75: read path — pageIndex, hydration
A76: PROJ-2 | B76: TASK-STATUS-CONSISTENCY — TWO LIVE SUBSYSTEMS (project t-* vs module opt-*), each with its own writers and automations. NOT drifted data. Unifying means moving creation paths, toggle, progress automation, quote-service, cockpit, detail view, declared options AND data together | C76: Projects | D76: P1 | E76: Parked | F76: coral-project-module.md:30 | G76: PARKED — scope corrected 2026-09-12, see coral-task-status-two-subsystems.md | H76: L3 | I76: Projects
A77: PROJ-3 | B77: quoted = sum of ALL linked quotes + addendums (NOTE: the first-only .find bug is already FIXED — ProjectDetailView.tsx:192 now uses a plural linkedQuotations memo + forEach; verify rather than rebuild); invoiced = sum of connected invoice RECORDS (not vorderingenstaten) — this half is still open;... | C77: Projects | D77: P1 | E77: Open | F77: coral-project-module.md:31 | H77: L3 | I77: Projects
A78: PROJ-5 | B78: finish ProjectCockpit into the command-center view: the live margin (quoted vs realized), revenue + cost ladders (with committed cost), progress %, budget-spent %, doc-status summary, crew-on-project. Match a real "is this project healthy" glance. (Reconfirm the layout with Florin — he flagged th... | C78: Projects | D78: P1 | E78: Open | F78: coral-project-module.md:33 | H78: L3 | I78: Projects
A79: PROJ-6 | B79: surface on the project: scheduled shifts (who's assigned, when) + actual clocked labour hours & cost vs quoted labour (data already aggregated: actualLaborHours, quotationFinancials.avgLabourRate). Ties the WorkHub/scheduler to the project (the WorkHub↔project link Florin has long wanted). | C79: Projects | D79: P1 | E79: Open | F79: coral-project-module.md:34 | H79: L3 | I79: Projects
A80: RCPT-L4b-3 | B80: replace Done with the scan's own verdict: Klaar (green) or Na te kijken — <reviewReason> (amber, e.g. "Bedragen komen niet overeen", "Ontbrekende velden"), Mislukt + error (red). The data is already in the scan response; it's the difference between "something happened" and "this one needs your ey... | C80: Scan · Receipt bulk | D80: P1 | E80: Done | F80: coral-receipt-bulk.md:79 | H80: L3 | I80: Expenses — receipts
A81: RCPT-L4b-4 | B81: when all jobs finish, show a one-line summary and a primary button "Bekijk in Inbox (N)" which closes the modal and lands on the filtered Inbox view. Do not auto-close — the per-file outcomes are the point of the screen (pd.md: the system surfaces, the user decides). | C81: Scan · Receipt bulk | D81: P1 | E81: Done | F81: coral-receipt-bulk.md:80 | H81: L3 | I81: Expenses — receipts
A82: BTW-LINE-INCL-CHECKBOX | B82: two parts, UI + calc: | C82: Triage / core | D82: P1 | E82: Open | F82: ground-zero-triage.md:502 | H82: L3 | I82: Finance — VAT
A83: BUILD-TYPECHECK-GATE | B83: PROCESS: this is the Nth broken-import/undefined-component crash that passed a green build (useEffect, submitLateEntry, W("db-clients"), now #130). The build is NOT failing on unresolved/typed-wrong imports. Enable blocking typecheck on imports (remove typescript.ignoreBuildErrors / add a CI tsc ... | C83: Triage / core | D83: P1 | E83: Done | F83: ground-zero-triage.md:671 | H83: ⟂ | I83: CI gates
A84: CLOCK-STATE-STALE-BADGE | B84: "Clocked In" shows even after clocking OUT (Florin 2026-07-12). NOT just the flashing — the badge's state is wrong. ROOT CAUSE (Planner-traced): src/components/time-tracker/hooks/useClockEntries.ts:42-43 is a per-component hook with isolated local useState and only fetches once on mount (L83-85);... | C84: Triage / core | D84: P1 | E84: Done | F84: ground-zero-triage.md:476 | H84: L3 | I84: HR — clock entries
A85: CONNECT-NEW-FLYOUT | B85: the Connect-New flyout (in detail modal Connected-Records) only opens on the SECOND click, and its button collides with the modal close button (it was removed from the Connected-Records card). FIX: fix the open-on-first-click (event/portal timing, same family as SELECT-LINGER) and reposition so C... | C85: Triage / core | D85: P1 | E85: Done | F85: ground-zero-triage.md:1147 | H85: L2 | I85: integrations
A86: DB-VIEW-PROPSTATE-NOT-STICKING | B86: column show/hide set in the database header does not persist. | C86: Triage / core | D86: P1 | E86: Open | F86: ground-zero-triage.md:287 | H86: L2 | I86: Database / Records module
A87: DEDUP-STRICT | B87: classify an incoming receipt/purchase-invoice against existing records by exact field equality (normalized: trim + case-fold names, canonicalize date to YYYY-MM-DD, strip formatting from the doc number): | C87: Triage / core | D87: P1 | E87: Open | F87: ground-zero-triage.md:602 | H87: L3 | I87: Expenses — dedup
A88: ENGINE-CATEGORY-WRAPPERS | C88: Triage / core | D88: P1 | E88: Open | F88: ground-zero-triage.md:559 | H88: L3 | I88: grid / relations engine
A89: ENGINE-DND-REBUILD | B89: replace the DnD foundation of the document engines (quote + invoice; shared QuotationRow/InvoiceRow/FinancialRowRenderer). | C89: Triage / core | D89: P1 | E89: Done | F89: ground-zero-triage.md:573 | H89: L3 | I89: grid / relations engine
A90: EXPENSE-CATEGORY-CONSOLIDATE | B90: TWO concurrent category systems exist: src/lib/expense-taxonomy.ts (EXPENSE_CATEGORIES/COST_TYPES, used by TicketCaptureModal + PurchaseInvoiceEngine) vs a separate hardcoded category select baked into the db-expenses schema in DatabaseClone.tsx (L294/L419/L440, its own inline options). So the DA... | C90: Triage / core | D90: P1 | E90: Open | F90: ground-zero-triage.md:612 | H90: L3 | I90: Expenses
A91: EXPENSE-CATEGORY-DB-WIRE | B91: the two-level category→costType selects made it INTO the modal (L912-926, using COST_TYPES) but NOT into the receipt database: the save writes category onto the created page (L73/L360/L409) yet db-expenses has no property to receive/display it → categories vanish. FIX: add category + costType (+ ... | C91: Triage / core | D91: P1 | E91: Open | F91: ground-zero-triage.md:349 | H91: L3 | I91: Expenses
A92: HR-TIMESHEET-APPROVALS | B92: the HR timesheets submodule must offer the full review actions (currently only reads approvalStatus, no actions): accept / deny a late entry, and accept/deny a non-GPS-bound (off-geofence/manual) entry. This is the review-queue side of CLOCK-APPROVAL. Add per-entry Accept/Deny controls (foreman/o... | C92: Triage / core | D92: P1 | E92: Open | F92: ground-zero-triage.md:634 | H92: L3 | I92: HR / Workforce
A93: HR-TIMESHEET-MANUAL-ADD | B93: an admin/foreman can manually add a time entry for a workforce member from HR timesheets (fallback when clock-in/out malfunctions): pick member + date + start/stop (+ optional project/note), creates a ClockEntry (flagged manual → pending approval per CLOCK-APPROVAL). Verify: add a manual entry fo... | C93: Triage / core | D93: P1 | E93: Open | F93: ground-zero-triage.md:635 | H93: L3 | I93: HR / Workforce
A94: HR-USER-NAME-RESOLUTION | B94: HR shows raw user CUIDs and, on the timesheets tab, every clock entry is attributed to "System" (Florin 2026-07-12). TWO surfaces, one class of bug — resolve userId → display name correctly and robustly. | C94: Triage / core | D94: P1 | E94: Done | F94: ground-zero-triage.md:401 | H94: L3 | I94: HR / Workforce
A95: MOBILE-HOME-NOT-WORKHUB | B95: on the main app on mobile, "Home" routes to WorkHub. Culprit: MobileBottomNav.tsx:20 { id:'workhub', label:'Home', href:'/admin/hr/time-tracker' } → that route redirect('/workhub'). FIX: point mobile Home at the mobile app home (/m, or /admin/dashboard), not the workhub redirect. (Coordinate with... | C95: Triage / core | D95: P1 | E95: Open | F95: ground-zero-triage.md:630 | H95: L2 | I95: Tasks · Mobile / PWA
A96: NOTIF-INCOMING-INVOICE-DEEPLINK | B96: make the notification open the actual purchase invoice: | C96: Triage / core | D96: P1 | E96: Open | F96: ground-zero-triage.md:492 | H96: L1 | I96: platform services — notifications
A97: OCC-10-INVISIBLE-RESOLVE-BUTTON | B97: "Resolve & Save" renders but is invisible. GlobalDatabaseSyncer.tsx:270 uses className="bg-brand-600 hover:bg-brand-700 text-white". There is no tailwind.config (Tailwind v4), no brand colour defined in globals.css, and bg-brand-600 occurs exactly once in the whole codebase — here. The class emit... | C97: Triage / core | D97: P1 | E97: Done | F97: ground-zero-triage.md:153 | H97: L1 | I97: write path — concurrency
A98: OCC-2b-FINISH-TAGGING | B98: OCC-2 only tagged cron-overdue and accountant-export. quote-service.ts (both write sites), payment-plan-service.ts, actions/pages.ts, actions/tasks.ts, api/scan, api/peppol/inbox, api/admin/backfill-peppol, accept-quote, accept-invoice, stripe/webhook, cron/vat-backfill, api/portals/, schema-clea... | C98: Triage / core | D98: P1 | E98: Done | F98: ground-zero-triage.md:124 | H98: L1 | I98: write path — concurrency
A99: OCC-3-FIELD-MERGE | B99: the high-leverage one; do it in the same pass, not later. Most of these toasts are non-collisions: the cron changed status, you edited betreft. | C99: Triage / core | D99: P1 | E99: Open | F99: ground-zero-triage.md:95 | H99: L1 | I99: write path — concurrency
A100: OCC-4-CONFLICT-UX | B100: replace the downloads-JSON escape hatch with real recovery. | C100: Triage / core | D100: P1 | E100: Open | F100: ground-zero-triage.md:104 | H100: L1 | I100: write path — concurrency
A101: OCC-4b-COPY | B101: the dialog shipped (good: Download Backup / Reload Page, no blind reload) but the header still reads "Someone else edited this page while you were working", which is false in the dominant case. Use the lastEditedBy origin now returned at :264: system origin → "This record changed in the backgroun... | C101: Triage / core | D101: P1 | E101: Open | F101: ground-zero-triage.md:125 | H101: L1 | I101: write path — concurrency
A102: PEPPOL-SEND-FIX | C102: Triage / core | D102: P1 | E102: Done | F102: ground-zero-triage.md:422 | H102: L2 | I102: Peppol / e-invoicing
A103: PORTAL-QUOTE-LINE-TOTAL | B103: ROOT CAUSE (traced, src/app/[locale]/quote/[id]/QuotationViewer.tsx): the leaf-line row uses the bare block.verkoopPrice — lineTotal = (block.verkoopPrice||0) qty (L115), unit price L131, total L134 — and does NOT recurse into subcomponents. But container totals use the recursive calculateBlockTo... | C103: Triage / core | D103: P1 | E103: Open | F103: ground-zero-triage.md:554 | H103: L2 | I103: Client Portal
A104: PROJECT-MODULE | B104: two parts: | C104: Triage / core | D104: P1 | E104: Open | F104: ground-zero-triage.md:623 | H104: L3 | I104: Projects
A105: PROJECT-TOTALS-AGGREGATE | B105: two separate bugs: | C105: Triage / core | D105: P1 | E105: Open | F105: ground-zero-triage.md:593 | H105: L3 | I105: Projects
A106: RECEIPT-BONNETJE-LINK | B106: the "Bonnetje" property links are broken (Florin 2026-07-12). DatabaseClone.tsx:460 defines { id:'receiptUrl', name:'Bonnetje', type:'url' }, but TicketCaptureModal stores the raw Blob storage KEY (receiptUrl = uploadRes.key, L307 → L344/364/401/414) into that url property. Since receipts are acc... | C106: Triage / core | D106: P1 | E106: Done | F106: ground-zero-triage.md:357 | H106: L3 | I106: Expenses — receipts
A107: RECORD-DETAIL-PASTE-FOCUS | B107: paste always lands in the NAME/title property, no matter where you click (Florin: even while creating a journal entry, the clipboard pastes into the name). Data-corruption risk. ROOT CAUSE (traced): there is NO paste handler anywhere — it's a focus-stealing bug. PageModal.tsx L588-600 does docume... | C107: Triage / core | D107: P1 | E107: Open | F107: ground-zero-triage.md:586 | H107: L3 | I107: grid — record surface
A108: SCAN-DATA-PERSIST | B108: the modal scans, then LOSES both the extracted data AND the scanned document — Florin has to re-upload the ticket and redo fields manually. Two things must persist through review→save: | C108: Triage / core | D108: P1 | E108: Open | F108: ground-zero-triage.md:350 | H108: L3 | I108: Expenses — OCR / scan
A109: SCAN-MOBILE-CAMERA-FALLBACK | B109: a phone-camera photo of a receipt must always be salvageable: Florin shot a receipt today, the capture was low quality, OCR read it poorly, and he ended up deleting it. OCR on a camera photo will NEVER be perfect — so the flow must degrade to manual correction, never dead-end. FIX: (1) confirm th... | C109: Triage / core | D109: P1 | E109: Open | F109: ground-zero-triage.md:354 | H109: L3 | I109: Expenses — OCR / scan
A110: SCAN-RECEIPT-TOTAL-NOT-NETTO | B110: on receipts the extraction grabs the netto (subtotal ex-VAT) and skips the totaal, so the amount is wrong (Florin 2026-07-12). On a kassabon/ticket the correct amount is ALWAYS the final TOTAAL / TE BETALEN / TOTAL paid (incl VAT), never a netto/subtotal line. FIX: in TICKET_SYSTEM_PROMPT (and th... | C110: Triage / core | D110: P1 | E110: Done | F110: ground-zero-triage.md:355 | H110: L3 | I110: Expenses — OCR / scan
A111: SCHED-ABSENCE-IN-GRID | B111: two gaps on absence: (1) scheduling an absence exists (scheduleType 'leave') — verify it works; (2) an approved LEAVE REQUEST (from the workforce time-off flow) does NOT appear in the scheduler. FIX: the scheduler grid must render approved absences/leave — read approved time-off/leave records for... | C111: Triage / core | D111: P1 | E111: Open | F111: ground-zero-triage.md:633 | H111: L3 | I111: HR — scheduling
A112: SCHED-CONVERT-TO-RECURRING | B112: (Florin request 1) — from an existing shift's edit dialog: "Make recurring" → pattern picker (reuse the existing selectedDays × recurringWeeks UI) → generates the future occurrences and stamps them plus the original with a shared seriesId. Show a preview count ("this will create 12 shifts") befor... | C112: Triage / core | D112: P1 | E112: Open | F112: ground-zero-triage.md:338 | H112: L3 | I112: HR — scheduling
A113: SCHED-DATE-RANGE | B113: (Florin request 2) — date-RANGE selection for both leave and shift creation. Verified today: leave writes a single shift_date (:485), so a week's holiday takes seven manual entries — that's the workaround Florin is (rightly) objecting to. | C113: Triage / core | D113: P1 | E113: Open | F113: ground-zero-triage.md:339 | H113: L3 | I113: HR — scheduling
A114: SCHED-MULTI-RECUR-VERIFY | B114: multi-assign, recurring, AND leave-scheduling already exist in CreateShiftForm.tsx (scheduleType: single|recurring|leave L175, recurringWeeks L166, worker checkboxes L795, userIds array → "across N employee(s)" L481). Florin reports the multi-member checkbox is gone/not showing and wants recurrin... | C114: Triage / core | D114: P1 | E114: Open | F114: ground-zero-triage.md:632 | H114: L3 | I114: HR — scheduling
... A143: TSP-B4 | B143: default to this month (or last 30 days), not this week: on a Monday the week-to-date view is near-empty and reads as breakage. And distinguish the three empty cases: request failed · no entries at all · _no entries in this period, but N exist outside it_ — the last one with a one-click widen. (Th... | C143: HR · Timesheets page | D143: P2 | E143: Open | F143: coral-timesheets-page.md:60 | H143: L3 | I143: HR — timesheets page
A144: MOBILE-DEVICE-DETECT | C144: Mobile | D144: P2 | E144: Open | F144: coral-mobile-optimization.md:36 | H144: L2 | I144: Tasks · Mobile / PWA
A145: MOBILE-STACKED-CARDS | C145: Mobile | D145: P2 | E145: Open | F145: coral-mobile-optimization.md:25 | H145: L2 | I145: Tasks · Mobile / PWA
A146: MEM-3d | B146: SERVER-SIDE ROLLUPS — project/cockpit totals aggregated server-side | C146: Performance · Memory | D146: P2 | E146: Open | F146: coral-mem3-lazy-data.md | H146: L1 | I146: read path — pageIndex, hydration
A147: MEM-3e | B147: WINDOWING WITHIN A DATABASE — cursor pagination + virtualised rows | C147: Performance · Memory | D147: P2 | E147: Open | F147: coral-mem3-lazy-data.md | H147: L1 | I147: read path — pageIndex, hydration
A148: MEM-4 | C148: Performance · Memory | D148: P2 | E148: Open | F148: coral-memory-investigation.md:46 | H148: L1 | I148: read path — pageIndex, hydration
A149: MEM-5 | C149: Performance · Memory | D149: P2 | E149: Open | F149: coral-memory-investigation.md:52 | H149: L1 | I149: read path — pageIndex, hydration
A150: — | B150: B1. Tenant Profile Staleness & Triple Write | C150: Pro Hardening | D150: P2 | E150: Done | F150: pro-hardening.md:979 | H150: L2 | I150: modules
...

Sheet Florin - my actions
A1: ID | B1: Action | C1: Status | D1: Priority
A2: ATT-5 | B2: Re-send invoices already sent with annexes selected (went out PDF-only) | C2: Done | D2: P0
A3: HR-5 | B3: Extend Neon PITR window + set snapshot schedule | C3: Done | D3: P1
A4: DEPLOY | B4: Push / deploy / migrations — Florin runs all of these | C4: Ongoing | D4: —
A5: ROADMAP | B5: Mark items noticed in use here, e.g. "to-do P4: ..." | C5: Ongoing | D5: —
A6: MEM-3c | B6: Verify the flagged lazy-load on real data for a week before removing the flag | C6: Open | D6: P1
A7: ACCT-DECISIONS | B7: Decide accountant sharing: mechanism, channel, export format, cadence, scope | C7: Open | D7: P2
A8: TENANTS | B8: Decide when to open free tier / onboard first tenants | C8: Open | D8: P2
A9: MAIL-3 | B9: After MAIL-1 ships: send one invoice, report the toast text | C9: Done | D9: P1
A10: BLOB-4 | B10: DECIDED: strict / all-or-nothing. No partial accountant exports. | C10: Done | D10: P0
A11: BLOB-4b | B11: After BLOB-4: list records already stamped accountantExportedAt whose PDF never shipped, and close the gap by hand (bookkeeping) | C11: Open | D11: P1
A12: SYSTEMS-PASS | B12: APPROVE or re-cut the root order in coral-systems-pass.md (key claim: the grid is a leaf of the write path, not a root) | C12: Open | D12: P0
... A24: SMS-0 | B24: Sweego trial: BE delivery + CORAL sender ID to your phone and one crew phone | C24: Open | D24: P2

Sheet Summary
A1: Metric | B1: Count
A2: Total items | B2: =COUNTA(Roadmap!A2:A334)
A3: Open | B3: =COUNTIF(Roadmap!E2:E334,"Open")
A4: In progress | B4: =COUNTIF(Roadmap!E2:E334,"In progress")
A5: Done | B5: =COUNTIF(Roadmap!E2:E334,"Done")
A7: P0 total | B7: =COUNTIF(Roadmap!D2:D334,"P0")
A8: P0 still open | B8: =COUNTIFS(Roadmap!D2:D334,"P0",Roadmap!E2:E334,"Open")
A9: P1 total | B9: =COUNTIF(Roadmap!D2:D334,"P1")
A10: P1 still open | B10: =COUNTIFS(Roadmap!D2:D334,"P1",Roadmap!E2:E334,"Open")
A11: P2 total | B11: =COUNTIF(Roadmap!D2:D334,"P2")
A12: P2 still open | B12: =COUNTIFS(Roadmap!D2:D334,"P2",Roadmap!E2:E334,"Open")
A13: P3 total | B13: =COUNTIF(Roadmap!D2:D334,"P3")
A14: P3 still open | B14: =COUNTIFS(Roadmap!D2:D334,"P3",Roadmap!E2:E334,"Open")
A15: P4 total | B15: =COUNTIF(Roadmap!D2:D334,"P4")
A16: P4 still open | B16: =COUNTIFS(Roadmap!D2:D334,"P4",Roadmap!E2:E334,"Open")
A18: By module — open
A19: Automations | B19: =COUNTIFS(Roadmap!C2:C334,"Automations",Roadmap!E2:E334,"Open")
A20: Calendar | B20: =COUNTIFS(Roadmap!C2:C334,"Calendar",Roadmap!E2:E334,"Open")
A21: Email attachments | B21: =COUNTIFS(Roadmap!C2:C334,"Email attachments",Roadmap!E2:E334,"Open")
A22: Engine · Grid | B22: =COUNTIFS(Roadmap!C2:C334,"Engine · Grid",Roadmap!E2:E334,"Open")
A23: Engine · Relations | B23: =COUNTIFS(Roadmap!C2:C334,"Engine · Relations",Roadmap!E2:E334,"Open")
A24: Finance · Invoice protest | B24: =COUNTIFS(Roadmap!C2:C334,"Finance · Invoice protest",Roadmap!E2:E334,"Open")
A25: Finance · Purchase invoices | B25: =COUNTIFS(Roadmap!C2:C334,"Finance · Purchase invoices",Roadmap!E2:E334,"Open")
A26: Finance · Purchase orders | B26: =COUNTIFS(Roadmap!C2:C334,"Finance · Purchase orders",Roadmap!E2:E334,"Open")
A27: HR · Timesheet reporting | B27: =COUNTIFS(Roadmap!C2:C334,"HR · Timesheet reporting",Roadmap!E2:E334,"Open")
A28: HR · Timesheets page | B28: =COUNTIFS(Roadmap!C2:C334,"HR · Timesheets page",Roadmap!E2:E334,"Open")
A29: Mobile | B29: =COUNTIFS(Roadmap!C2:C334,"Mobile",Roadmap!E2:E334,"Open")
A30: Mobile / PWA | B30: =COUNTIFS(Roadmap!C2:C334,"Mobile / PWA",Roadmap!E2:E334,"Open")
A31: Performance · Memory | B31: =COUNTIFS(Roadmap!C2:C334,"Performance · Memory",Roadmap!E2:E334,"Open")
A32: Pro Hardening | B32: =COUNTIFS(Roadmap!C2:C334,"Pro Hardening",Roadmap!E2:E334,"Open")
A33: Projects | B33: =COUNTIFS(Roadmap!C2:C334,"Projects",Roadmap!E2:E334,"Open")
A34: Reliability | B34: =COUNTIFS(Roadmap!C2:C334,"Reliability",Roadmap!E2:E334,"Open")
A35: Scan · Receipt bulk | B35: =COUNTIFS(Roadmap!C2:C334,"Scan · Receipt bulk",Roadmap!E2:E334,"Open")
A36: Triage / core | B36: =COUNTIFS(Roadmap!C2:C334,"Triage / core",Roadmap!E2:E334,"Open")
A38: BY MAP LAYER
A39: L0 | B39: 21
A40: L1 | B40: 84
A41: GATE | B41: 12
A42: L2 | B42: 20
A43: MODULE GATE | B43: 2
A44: L3 | B44: 184
A45: L4 | B45: 2
A46: ⟂ | B46: 8
